[
    {
        "id": 30,
        "intersections": [
            [
                18,
                24
            ]
        ]
    },
    {
        "id": 31,
        "intersections": [
            [
                6,
                10,
                24
            ]
        ]
    },
    {
        "id": 32,
        "intersections": [
            [
                6,
                7,
                24
            ]
        ]
    },
    {
        "id": 33,
        "intersections": [
            [
                30,
                31,
                32
            ]
        ]
    },
    {
        "id": 34,
        "intersections": [
            [
                11,
                18,
                29,
                33
            ]
        ]
    },
    {
        "id": 35,
        "intersections": [
            [
                9,
                29,
                33,
                34
            ]
        ]
    },
    {
        "id": 36,
        "intersections": [
            [
                7,
                11,
                29,
                33
            ]
        ]
    }
]